<?xml version="1.0" encoding="UTF-8"?><activity xmlns:natgeo="http://www.pageseeder.com/natgeo/1.0" xmlns:ps="http://www.pageseeder.com/editing/2.0" templateid="MCQSSR" activityid="" casecheck="yes" defaultscore="1" generatorid="PageSeeder" datetimestamp=""><directions><content type="html" tag="directions"><![CDATA[ Listen to the audio. Click the correct answer for each question. Click <b>Submit</b> to check your answers. ]]></content></directions><questionsets><questionset><question><content type="text" tag="questionText">  Is Jenny wearing a hat?</content><content type="audio" tag="paragraphAudio">activities/resources/audios/L0-U08-LB.mp3</content></question><options><option><content type="text" tag="optionText">Yes, she is.</content></option><option><content type="text" tag="optionText">No, she's not.</content></option><option><content type="text" tag="optionText">We don't know.</content></option></options><answers><answer><content type="number" tag="answerIndex">1</content></answer></answers></questionset><questionset><question><content type="text" tag="questionText">  What color pants is Helen wearing?</content><content type="audio" tag="paragraphAudio">activities/resources/audios/L0-U08-LB.mp3</content></question><options><option><content type="text" tag="optionText">brown</content></option><option><content type="text" tag="optionText">white</content></option><option><content type="text" tag="optionText">purple</content></option><option><content type="text" tag="optionText">red</content></option></options><answers><answer><content type="number" tag="answerIndex">1</content></answer></answers></questionset><questionset><question><content type="text" tag="questionText">  What color jacket is Dave wearing?</content><content type="audio" tag="paragraphAudio">activities/resources/audios/L0-U08-LB.mp3</content></question><options><option><content type="text" tag="optionText">black</content></option><option><content type="text" tag="optionText">yellow</content></option><option><content type="text" tag="optionText">purple</content></option><option><content type="text" tag="optionText">white</content></option></options><answers><answer><content type="number" tag="answerIndex">1</content></answer></answers></questionset><questionset><question><content type="text" tag="questionText">  Who is wearing a scarf?</content><content type="audio" tag="paragraphAudio">activities/resources/audios/L0-U08-LB.mp3</content></question><options><option><content type="text" tag="optionText">Dave</content></option><option><content type="text" tag="optionText">Helen</content></option><option><content type="text" tag="optionText">Jenny</content></option><option><content type="text" tag="optionText">Zahra</content></option></options><answers><answer><content type="number" tag="answerIndex">3</content></answer></answers></questionset><questionset><question><content type="text" tag="questionText">  What is Helen doing?</content><content type="audio" tag="paragraphAudio">activities/resources/audios/L0-U08-LB.mp3</content></question><options><option><content type="text" tag="optionText">having dinner</content></option><option><content type="text" tag="optionText">leaving for work</content></option><option><content type="text" tag="optionText">taking a nap</content></option><option><content type="text" tag="optionText">calling a taxi</content></option></options><answers><answer><content type="number" tag="answerIndex">4</content></answer></answers></questionset></questionsets></activity>