<?xml version="1.0" encoding="UTF-8"?><activity xmlns:natgeo="http://www.pageseeder.com/natgeo/1.0" xmlns:ps="http://www.pageseeder.com/editing/2.0" templateid="MCQSS" activityid="" casecheck="yes" defaultscore="1" generatorid="PageSeeder" datetimestamp=""><directions><content type="html" tag="directions"><![CDATA[ Click the correct form of the verb to complete each sentence. Click <b>Submit</b> to check your answers. ]]></content></directions><questionsets><questionset><question><content type="text" tag="questionText">I __________ weight lifting is hard. </content></question><options><option><content type="text" tag="optionText">am thinking</content></option><option><content type="text" tag="optionText">think</content></option><option><content type="text" tag="optionText">thinks</content></option></options><answers><answer><content type="number" tag="answerIndex">2</content></answer></answers></questionset><questionset><question><content type="text" tag="questionText">She __________ the cold weather. </content></question><options><option><content type="text" tag="optionText">hate</content></option><option><content type="text" tag="optionText">hates</content></option><option><content type="text" tag="optionText">hated</content></option></options><answers><answer><content type="number" tag="answerIndex">2</content></answer></answers></questionset><questionset><question><content type="text" tag="questionText">They  __________ soccer right now.  </content></question><options><option><content type="text" tag="optionText">are playing</content></option><option><content type="text" tag="optionText">plays</content></option><option><content type="text" tag="optionText">play</content></option></options><answers><answer><content type="number" tag="answerIndex">3</content></answer></answers></questionset><questionset><question><content type="text" tag="questionText">You __________ I don't see well. </content></question><options><option><content type="text" tag="optionText">know</content></option><option><content type="text" tag="optionText">are knowing</content></option><option><content type="text" tag="optionText">knows</content></option></options><answers><answer><content type="number" tag="answerIndex">1</content></answer></answers></questionset><questionset><question><content type="text" tag="questionText">We __________ to ride our bikes to school. </content></question><options><option><content type="text" tag="optionText">are preferring</content></option><option><content type="text" tag="optionText">prefers </content></option><option><content type="text" tag="optionText">prefer</content></option></options><answers><answer><content type="number" tag="answerIndex">3</content></answer></answers></questionset></questionsets></activity>