<?xml version="1.0" encoding="UTF-8"?><activity xmlns:natgeo="http://www.pageseeder.com/natgeo/1.0" xmlns:ps="http://www.pageseeder.com/editing/2.0" templateid="DNDNON" activityid="" defaultscore="1" generatorid="PageSeeder" datetimestamp=""><directions><content type="html" tag="directions"><![CDATA[ Drag the correct word of possession to each sentence. Click <b>Submit</b> to check your answers. ]]></content></directions><questionscommon><content type="number" tag="totalOptionsCount">5</content><content type="text" tag="optionText">her</content><content type="text" tag="optionText">his</content><content type="text" tag="optionText">my</content><content type="text" tag="optionText">our</content><content type="text" tag="optionText">your</content></questionscommon><questionsets><questionset><question><content type="text" tag="questionText">I raise __ hand to speak in class. </content></question><answers><answer><content type="text" tag="answerText">my</content></answer></answers></questionset><questionset><question><content type="text" tag="questionText">Do you do __ homework every night? </content></question><answers><answer><content type="text" tag="answerText">your</content></answer></answers></questionset><questionset><question><content type="text" tag="questionText">Tom always forgets to do __ homework. </content></question><answers><answer><content type="text" tag="answerText">his</content></answer></answers></questionset><questionset><question><content type="text" tag="questionText">We need to finish __ group project tomorrow.</content></question><answers><answer><content type="text" tag="answerText">our</content></answer></answers></questionset><questionset><question><content type="text" tag="questionText">The blue backpack belongs to __.  </content></question><answers><answer><content type="text" tag="answerText">her</content></answer></answers></questionset></questionsets></activity>