<?xml version="1.0" encoding="UTF-8"?><activity templateid="MCQMSP" activityid="" casecheck="yes" defaultscore="1" generatorid="PageSeeder" datetimestamp=""><directions><content type="html" tag="directions"><![CDATA[ Click on the open book icon in the circle to read and listen to the reading passage. Click all the correct answers for each question. Click <b>Submit</b> to check your answers. ]]></content></directions><questionscommon><content type="external" tag="commonPDF">activities/resources/externals/L1-U11-LA-RC.pdf</content></questionscommon><questionsets><questionset><question><content type="text" tag="questionText">Which sentences about the average pirate are true?</content></question><options><option><content type="text" tag="optionText">They had difficult lives.</content></option><option><content type="text" tag="optionText">They were not slaves.</content></option><option><content type="text" tag="optionText">They led healthy lives.</content></option><option><content type="text" tag="optionText">They came from different backgrounds.</content></option></options><answers><answer><content type="number" tag="answerIndex">1</content></answer><answer><content type="number" tag="answerIndex">4</content></answer></answers></questionset><questionset><question><content type="text" tag="questionText">Equality was important on pirate ships. What shows this?</content></question><options><option><content type="text" tag="optionText">The pirates came from many different backgrounds.</content></option><option><content type="text" tag="optionText">The pirates worked together to make their rules.</content></option><option><content type="text" tag="optionText">The pirates shared their earnings.</content></option><option><content type="text" tag="optionText">The pirates created the stolen goods.</content></option></options><answers><answer><content type="number" tag="answerIndex">2</content></answer><answer><content type="number" tag="answerIndex">3</content></answer></answers></questionset><questionset><question><content type="text" tag="questionText">What did most pirates NOT do?</content></question><options><option><content type="text" tag="optionText">divide their income</content></option><option><content type="text" tag="optionText">bury their money</content></option><option><content type="text" tag="optionText">steal things</content></option><option><content type="text" tag="optionText">purchase stolen goods from their captain </content></option></options><answers><answer><content type="number" tag="answerIndex">2</content></answer><answer><content type="number" tag="answerIndex">4</content></answer></answers></questionset><questionset><question><content type="text" tag="questionText">What are examples of spices?</content></question><options><option><content type="text" tag="optionText">pepper</content></option><option><content type="text" tag="optionText">sugar</content></option><option><content type="text" tag="optionText">flour</content></option><option><content type="text" tag="optionText">ginger</content></option></options><answers><answer><content type="number" tag="answerIndex">1</content></answer><answer><content type="number" tag="answerIndex">4</content></answer></answers></questionset><questionset><question><content type="text" tag="questionText">Why did some pirates have wooden legs and eye patches?</content></question><options><option><content type="text" tag="optionText">because they lost their hair</content></option><option><content type="text" tag="optionText">because they lost their eyes</content></option><option><content type="text" tag="optionText">because they lost their legs</content></option><option><content type="text" tag="optionText">because they wore earrings</content></option></options><answers><answer><content type="number" tag="answerIndex">2</content></answer><answer><content type="number" tag="answerIndex">3</content></answer></answers></questionset></questionsets></activity>