<?xml version="1.0" encoding="UTF-8"?><activity templateid="FIBOPB" activityid="" casecheck="yes" defaultscore="1" generatorid="PageSeeder" datetimestamp="2008-08-18 16:28:52"><directions><content type="html" tag="directions"><![CDATA[ Type the correct word from the box to complete each sentence. Click <b>Submit</b> to check your answers. ]]></content></directions><questionscommon><content type="text" tag="optionText">analyzed</content><content type="text" tag="optionText">attached</content><content type="text" tag="optionText">excluded</content><content type="text" tag="optionText">infection</content><content type="text" tag="optionText">murdered</content></questionscommon><questionsets><questionset><question><content type="text" tag="questionText">Trains are made up of many cars __ to each other.</content></question><answers><answer><content type="text" tag="answer">attached</content></answer></answers></questionset><questionset><question><content type="text" tag="questionText">The scientist __ the object carefully with a microscope.</content></question><answers><answer><content type="text" tag="answer">analyzed</content></answer></answers></questionset><questionset><question><content type="text" tag="questionText">Phil didn't clean a cut on his finger and now he has an __.</content></question><answers><answer><content type="text" tag="answer">infection</content></answer></answers></questionset><questionset><question><content type="text" tag="questionText">Women were __ from voting in some of the U.S. states until 1920.</content></question><answers><answer><content type="text" tag="answer">excluded</content></answer></answers></questionset><questionset><question><content type="text" tag="questionText">John F. Kennedy, 35th President of the United States, was __ in 1963.</content></question><answers><answer><content type="text" tag="answer">murdered</content></answer></answers></questionset></questionsets></activity>