<?xml version="1.0" encoding="UTF-8"?><activity xmlns:ps="http://www.pageseeder.com/editing/2.0" xmlns:natgeo="http://www.pageseeder.com/natgeo/1.0" templateid="MCQSSR" activityid="" casecheck="yes" defaultscore="1" generatorid="PageSeeder" datetimestamp=""><directions><content type="html" tag="directions"><![CDATA[ Listen to the audio. Click the correct answer for each question. Click <b>Submit</b> to check your answers. ]]></content></directions><questionsets><questionset><question><content type="text" tag="questionText"> In what city is the restaurant located?</content><content type="audio" tag="paragraphAudio">activities/resources/audios/L2-U11-LB1.mp3</content></question><options><option><content type="text" tag="optionText">Hong Kong</content></option><option><content type="text" tag="optionText">Singapore</content></option><option><content type="text" tag="optionText">Bangkok </content></option></options><answers><answer><content type="number" tag="answerIndex">3</content></answer></answers></questionset><questionset><question><content type="text" tag="questionText"> Which of his relatives does Mr. Sangumram employ?</content><content type="audio" tag="paragraphAudio">activities/resources/audios/L2-U11-LB1.mp3</content></question><options><option><content type="text" tag="optionText">his nephew</content></option><option><content type="text" tag="optionText">his son</content></option><option><content type="text" tag="optionText">his wife</content></option></options><answers><answer><content type="number" tag="answerIndex">1</content></answer></answers></questionset><questionset><question><content type="text" tag="questionText"> Why doesn't Mr. Sangumram give out his recipes?</content><content type="audio" tag="paragraphAudio">activities/resources/audios/L2-U11-LB1.mp3</content></question><options><option><content type="text" tag="optionText">because it is illegal</content></option><option><content type="text" tag="optionText">because they are not very good</content></option><option><content type="text" tag="optionText">because they are top secret</content></option></options><answers><answer><content type="number" tag="answerIndex">3</content></answer></answers></questionset><questionset><question><content type="text" tag="questionText"> What kind of food do other local restaurants serve?</content><content type="audio" tag="paragraphAudio">activities/resources/audios/L2-U11-LB1.mp3</content></question><options><option><content type="text" tag="optionText">Italian and Mexican</content></option><option><content type="text" tag="optionText">Chinese and Japanese</content></option><option><content type="text" tag="optionText">French and America</content></option></options><answers><answer><content type="number" tag="answerIndex">2</content></answer></answers></questionset><questionset><question><content type="text" tag="questionText"> What compliment does Mr. Sangumram give his job?</content><content type="audio" tag="paragraphAudio">activities/resources/audios/L2-U11-LB1.mp3</content></question><options><option><content type="text" tag="optionText">It's the best one he's ever had.</content></option><option><content type="text" tag="optionText">The benefits are great.</content></option><option><content type="text" tag="optionText">The hours are great.</content></option></options><answers><answer><content type="number" tag="answerIndex">1</content></answer></answers></questionset></questionsets></activity>